PopComm/__init__.py
PopComm/diff_interaction.py
PopComm/filter_lr.py
PopComm/score_lr.py
PopComm/utils.py
PopComm/vis_lr.py
PopComm/vis_sample.py
PopComm/data/__init__.py
popcomm-0.1.6.dist-info/METADATA
popcomm-0.1.6.dist-info/WHEEL
popcomm-0.1.6.dist-info/top_level.txt
popcomm-0.1.6.dist-info/RECORD
