Metadata-Version: 2.4
Name: PopComm
Version: 0.1.6
Summary: Population-level cell-cell communication analysis tool
Home-page: https://github.com/yourgithub/popcomm
Author: Mengwei Li
Author-email: limengwei833@gmail.com
Classifier: Programming Language :: Python :: 3
Classifier: License :: OSI Approved :: MIT License
Requires-Python: >=3.7
Requires-Dist: joblib
Requires-Dist: matplotlib
Requires-Dist: networkx
Requires-Dist: numpy
Requires-Dist: pandas
Requires-Dist: scanpy
Requires-Dist: scikit_learn
Requires-Dist: scipy
Requires-Dist: seaborn
Requires-Dist: statsmodels
Dynamic: author
Dynamic: author-email
Dynamic: classifier
Dynamic: description
Dynamic: description-content-type
Dynamic: home-page
Dynamic: requires-dist
Dynamic: requires-python
Dynamic: summary
